{
  "meta": {
    "data_version": "1.1.0",
    "created": "2025-01-21",
    "revision": 1
  },
  "info": {
    "balls_per_over": 6,
    "city": "Durban",
    "dates": [
      "2025-01-21"
    ],
    "event": {
      "name": "SA20",
      "match_number": 16
    },
    "gender": "male",
    "match_type": "T20",
    "officials": {
      "match_referees": [
        "SA Fritz"
      ],
      "reserve_umpires": [
        "DJ Smith"
      ],
      "tv_umpires": [
        "LB Gcuma"
      ],
      "umpires": [
        "A Paleker",
        "James Middlebrook"
      ]
    },
    "outcome": {
      "result": "no result"
    },
    "overs": 20,
    "players": {
      "MI Cape Town": [
        "HE van der Dussen",
        "RD Rickelton",
        "RR Hendricks",
        "CA Ingram",
        "Rashid Khan",
        "D Brevis",
        "GF Linde",
        "D Potgieter",
        "C Bosch",
        "K Rabada",
        "TA Boult"
      ],
      "Durban's Super Giants": [
        "MP Breetzke",
        "BA King",
        "Q de Kock",
        "KS Williamson",
        "PWA Mulder",
        "H Klaasen",
        "D Pretorius",
        "KA Maharaj",
        "CJ Dala",
        "Naveen-ul-Haq",
        "Noor Ahmad"
      ]
    },
    "registry": {
      "people": {
        "A Paleker": "634b11ac",
        "BA King": "7fca84b7",
        "C Bosch": "172dff15",
        "CA Ingram": "c995d726",
        "CJ Dala": "1cb14aa4",
        "D Brevis": "844e79d1",
        "D Potgieter": "60fbf53a",
        "D Pretorius": "11614d87",
        "DJ Smith": "d17bec15",
        "GF Linde": "e5437608",
        "H Klaasen": "235c2bb6",
        "HE van der Dussen": "9948e262",
        "James Middlebrook": "ddcd1520",
        "K Rabada": "e62dd25d",
        "KA Maharaj": "0b60eb09",
        "KS Williamson": "d027ba9f",
        "LB Gcuma": "02ba88e3",
        "MP Breetzke": "35f173a0",
        "Naveen-ul-Haq": "c0c411cb",
        "Noor Ahmad": "efc04be7",
        "PWA Mulder": "c96f6ac5",
        "Q de Kock": "372455c4",
        "RD Rickelton": "e66732f8",
        "RR Hendricks": "b8cc58c9",
        "Rashid Khan": "5f547c8b",
        "SA Fritz": "d15e60c8",
        "TA Boult": "a818c1be"
      }
    },
    "season": "2024/25",
    "team_type": "club",
    "teams": [
      "MI Cape Town",
      "Durban's Super Giants"
    ],
    "toss": {
      "decision": "field",
      "winner": "Durban's Super Giants"
    },
    "venue": "Kingsmead, Durban"
  },
  "innings": [
    {
      "team": "MI Cape Town",
      "overs": [
        {
          "over": 0,
          "deliveries": [
            {
              "batter": "HE van der Dussen",
              "bowler": "D Pretorius",
              "non_striker": "RD Rickelton",
              "runs": {
                "batter": 0,
                "extras": 0,
                "total": 0
              }
            },
            {
              "batter": "HE van der Dussen",
              "bowler": "D Pretorius",
              "non_striker": "RD Rickelton",
              "runs": {
                "batter": 0,
                "extras": 0,
                "total": 0
              }
            },
            {
              "batter": "HE van der Dussen",
              "bowler": "D Pretorius",
              "non_striker": "RD Rickelton",
              "runs": {
                "batter": 0,
                "extras": 0,
                "total": 0
              }
            },
            {
              "batter": "HE van der Dussen",
              "bowler": "D Pretorius",
              "non_striker": "RD Rickelton",
              "runs": {
                "batter": 1,
                "extras": 0,
                "total": 1
              }
            },
            {
              "batter": "RD Rickelton",
              "bowler": "D Pretorius",
              "non_striker": "HE van der Dussen",
              "runs": {
                "batter": 1,
                "extras": 0,
                "total": 1
              }
            },
            {
              "batter": "HE van der Dussen",
              "bowler": "D Pretorius",
              "non_striker": "RD Rickelton",
              "runs": {
                "batter": 0,
                "extras": 0,
                "total": 0
              }
            }
          ]
        },
        {
          "over": 1,
          "deliveries": [
            {
              "batter": "RD Rickelton",
              "bowler": "Naveen-ul-Haq",
              "non_striker": "HE van der Dussen",
              "runs": {
                "batter": 4,
                "extras": 0,
                "total": 4
              }
            },
            {
              "batter": "RD Rickelton",
              "bowler": "Naveen-ul-Haq",
              "extras": {
                "legbyes": 1
              },
              "non_striker": "HE van der Dussen",
              "runs": {
                "batter": 0,
                "extras": 1,
                "total": 1
              }
            },
            {
              "batter": "HE van der Dussen",
              "bowler": "Naveen-ul-Haq",
              "non_striker": "RD Rickelton",
              "runs": {
                "batter": 0,
                "extras": 0,
                "total": 0
              }
            },
            {
              "batter": "HE van der Dussen",
              "bowler": "Naveen-ul-Haq",
              "non_striker": "RD Rickelton",
              "runs": {
                "batter": 1,
                "extras": 0,
                "total": 1
              }
            },
            {
              "batter": "RD Rickelton",
              "bowler": "Naveen-ul-Haq",
              "non_striker": "HE van der Dussen",
              "runs": {
                "batter": 4,
                "extras": 0,
                "total": 4
              }
            },
            {
              "batter": "RD Rickelton",
              "bowler": "Naveen-ul-Haq",
              "non_striker": "HE van der Dussen",
              "runs": {
                "batter": 4,
                "extras": 0,
                "total": 4
              }
            }
          ]
        },
        {
          "over": 2,
          "deliveries": [
            {
              "batter": "HE van der Dussen",
              "bowler": "D Pretorius",
              "non_striker": "RD Rickelton",
              "runs": {
                "batter": 1,
                "extras": 0,
                "total": 1
              }
            },
            {
              "batter": "RD Rickelton",
              "bowler": "D Pretorius",
              "non_striker": "HE van der Dussen",
              "runs": {
                "batter": 1,
                "extras": 0,
                "total": 1
              }
            },
            {
              "batter": "HE van der Dussen",
              "bowler": "D Pretorius",
              "non_striker": "RD Rickelton",
              "runs": {
                "batter": 4,
                "extras": 0,
                "total": 4
              }
            },
            {
              "batter": "HE van der Dussen",
              "bowler": "D Pretorius",
              "non_striker": "RD Rickelton",
              "runs": {
                "batter": 2,
                "extras": 0,
                "total": 2
              }
            },
            {
              "batter": "HE van der Dussen",
              "bowler": "D Pretorius",
              "extras": {
                "legbyes": 1
              },
              "non_striker": "RD Rickelton",
              "runs": {
                "batter": 0,
                "extras": 1,
                "total": 1
              }
            },
            {
              "batter": "RD Rickelton",
              "bowler": "D Pretorius",
              "non_striker": "HE van der Dussen",
              "runs": {
                "batter": 4,
                "extras": 0,
                "total": 4
              }
            }
          ]
        },
        {
          "over": 3,
          "deliveries": [
            {
              "batter": "HE van der Dussen",
              "bowler": "CJ Dala",
              "non_striker": "RD Rickelton",
              "runs": {
                "batter": 4,
                "extras": 0,
                "total": 4
              }
            },
            {
              "batter": "HE van der Dussen",
              "bowler": "CJ Dala",
              "non_striker": "RD Rickelton",
              "runs": {
                "batter": 0,
                "extras": 0,
                "total": 0
              }
            },
            {
              "batter": "HE van der Dussen",
              "bowler": "CJ Dala",
              "non_striker": "RD Rickelton",
              "runs": {
                "batter": 0,
                "extras": 0,
                "total": 0
              }
            },
            {
              "batter": "HE van der Dussen",
              "bowler": "CJ Dala",
              "non_striker": "RD Rickelton",
              "runs": {
                "batter": 1,
                "extras": 0,
                "total": 1
              }
            },
            {
              "batter": "RD Rickelton",
              "bowler": "CJ Dala",
              "non_striker": "HE van der Dussen",
              "runs": {
                "batter": 0,
                "extras": 0,
                "total": 0
              }
            },
            {
              "batter": "RD Rickelton",
              "bowler": "CJ Dala",
              "non_striker": "HE van der Dussen",
              "runs": {
                "batter": 0,
                "extras": 0,
                "total": 0
              },
              "wickets": [
                {
                  "player_out": "RD Rickelton",
                  "kind": "bowled"
                }
              ]
            }
          ]
        },
        {
          "over": 4,
          "deliveries": [
            {
              "batter": "HE van der Dussen",
              "bowler": "KA Maharaj",
              "non_striker": "RR Hendricks",
              "runs": {
                "batter": 1,
                "extras": 0,
                "total": 1
              }
            },
            {
              "batter": "RR Hendricks",
              "bowler": "KA Maharaj",
              "non_striker": "HE van der Dussen",
              "runs": {
                "batter": 0,
                "extras": 0,
                "total": 0
              }
            },
            {
              "batter": "RR Hendricks",
              "bowler": "KA Maharaj",
              "non_striker": "HE van der Dussen",
              "runs": {
                "batter": 2,
                "extras": 0,
                "total": 2
              }
            },
            {
              "batter": "RR Hendricks",
              "bowler": "KA Maharaj",
              "non_striker": "HE van der Dussen",
              "runs": {
                "batter": 1,
                "extras": 0,
                "total": 1
              }
            },
            {
              "batter": "HE van der Dussen",
              "bowler": "KA Maharaj",
              "non_striker": "RR Hendricks",
              "runs": {
                "batter": 0,
                "extras": 0,
                "total": 0
              }
            },
            {
              "batter": "HE van der Dussen",
              "bowler": "KA Maharaj",
              "non_striker": "RR Hendricks",
              "runs": {
                "batter": 1,
                "extras": 0,
                "total": 1
              }
            }
          ]
        },
        {
          "over": 5,
          "deliveries": [
            {
              "batter": "HE van der Dussen",
              "bowler": "CJ Dala",
              "non_striker": "RR Hendricks",
              "runs": {
                "batter": 6,
                "extras": 0,
                "total": 6
              }
            },
            {
              "batter": "HE van der Dussen",
              "bowler": "CJ Dala",
              "non_striker": "RR Hendricks",
              "runs": {
                "batter": 1,
                "extras": 0,
                "total": 1
              }
            },
            {
              "batter": "RR Hendricks",
              "bowler": "CJ Dala",
              "non_striker": "HE van der Dussen",
              "runs": {
                "batter": 1,
                "extras": 0,
                "total": 1
              }
            },
            {
              "batter": "HE van der Dussen",
              "bowler": "CJ Dala",
              "non_striker": "RR Hendricks",
              "runs": {
                "batter": 1,
                "extras": 0,
                "total": 1
              }
            },
            {
              "batter": "RR Hendricks",
              "bowler": "CJ Dala",
              "non_striker": "HE van der Dussen",
              "runs": {
                "batter": 1,
                "extras": 0,
                "total": 1
              }
            },
            {
              "batter": "HE van der Dussen",
              "bowler": "CJ Dala",
              "non_striker": "RR Hendricks",
              "runs": {
                "batter": 0,
                "extras": 0,
                "total": 0
              }
            }
          ]
        },
        {
          "over": 6,
          "deliveries": [
            {
              "batter": "RR Hendricks",
              "bowler": "KA Maharaj",
              "non_striker": "HE van der Dussen",
              "runs": {
                "batter": 0,
                "extras": 0,
                "total": 0
              }
            },
            {
              "batter": "RR Hendricks",
              "bowler": "KA Maharaj",
              "non_striker": "HE van der Dussen",
              "runs": {
                "batter": 0,
                "extras": 0,
                "total": 0
              }
            },
            {
              "batter": "RR Hendricks",
              "bowler": "KA Maharaj",
              "non_striker": "HE van der Dussen",
              "runs": {
                "batter": 1,
                "extras": 0,
                "total": 1
              }
            },
            {
              "batter": "HE van der Dussen",
              "bowler": "KA Maharaj",
              "non_striker": "RR Hendricks",
              "runs": {
                "batter": 1,
                "extras": 0,
                "total": 1
              }
            },
            {
              "batter": "RR Hendricks",
              "bowler": "KA Maharaj",
              "non_striker": "HE van der Dussen",
              "runs": {
                "batter": 1,
                "extras": 0,
                "total": 1
              }
            },
            {
              "batter": "HE van der Dussen",
              "bowler": "KA Maharaj",
              "non_striker": "RR Hendricks",
              "runs": {
                "batter": 1,
                "extras": 0,
                "total": 1
              }
            }
          ]
        },
        {
          "over": 7,
          "deliveries": [
            {
              "batter": "HE van der Dussen",
              "bowler": "Noor Ahmad",
              "non_striker": "RR Hendricks",
              "runs": {
                "batter": 4,
                "extras": 0,
                "total": 4
              }
            },
            {
              "batter": "HE van der Dussen",
              "bowler": "Noor Ahmad",
              "non_striker": "RR Hendricks",
              "runs": {
                "batter": 0,
                "extras": 0,
                "total": 0
              }
            },
            {
              "batter": "HE van der Dussen",
              "bowler": "Noor Ahmad",
              "non_striker": "RR Hendricks",
              "runs": {
                "batter": 1,
                "extras": 0,
                "total": 1
              }
            },
            {
              "batter": "RR Hendricks",
              "bowler": "Noor Ahmad",
              "non_striker": "HE van der Dussen",
              "runs": {
                "batter": 1,
                "extras": 0,
                "total": 1
              }
            },
            {
              "batter": "HE van der Dussen",
              "bowler": "Noor Ahmad",
              "non_striker": "RR Hendricks",
              "runs": {
                "batter": 0,
                "extras": 0,
                "total": 0
              }
            },
            {
              "batter": "HE van der Dussen",
              "bowler": "Noor Ahmad",
              "non_striker": "RR Hendricks",
              "runs": {
                "batter": 1,
                "extras": 0,
                "total": 1
              }
            }
          ]
        },
        {
          "over": 8,
          "deliveries": [
            {
              "batter": "HE van der Dussen",
              "bowler": "KA Maharaj",
              "non_striker": "RR Hendricks",
              "runs": {
                "batter": 1,
                "extras": 0,
                "total": 1
              }
            },
            {
              "batter": "RR Hendricks",
              "bowler": "KA Maharaj",
              "non_striker": "HE van der Dussen",
              "runs": {
                "batter": 0,
                "extras": 0,
                "total": 0
              },
              "wickets": [
                {
                  "player_out": "RR Hendricks",
                  "fielders": [
                    {
                      "name": "PWA Mulder"
                    }
                  ],
                  "kind": "caught"
                }
              ]
            },
            {
              "batter": "CA Ingram",
              "bowler": "KA Maharaj",
              "non_striker": "HE van der Dussen",
              "runs": {
                "batter": 0,
                "extras": 0,
                "total": 0
              }
            },
            {
              "batter": "CA Ingram",
              "bowler": "KA Maharaj",
              "non_striker": "HE van der Dussen",
              "runs": {
                "batter": 0,
                "extras": 0,
                "total": 0
              }
            },
            {
              "batter": "CA Ingram",
              "bowler": "KA Maharaj",
              "non_striker": "HE van der Dussen",
              "runs": {
                "batter": 0,
                "extras": 0,
                "total": 0
              }
            },
            {
              "batter": "CA Ingram",
              "bowler": "KA Maharaj",
              "non_striker": "HE van der Dussen",
              "runs": {
                "batter": 1,
                "extras": 0,
                "total": 1
              }
            }
          ]
        },
        {
          "over": 9,
          "deliveries": [
            {
              "batter": "CA Ingram",
              "bowler": "Noor Ahmad",
              "non_striker": "HE van der Dussen",
              "runs": {
                "batter": 0,
                "extras": 0,
                "total": 0
              }
            },
            {
              "batter": "CA Ingram",
              "bowler": "Noor Ahmad",
              "non_striker": "HE van der Dussen",
              "runs": {
                "batter": 0,
                "extras": 0,
                "total": 0
              },
              "wickets": [
                {
                  "player_out": "CA Ingram",
                  "fielders": [
                    {
                      "name": "BA King"
                    }
                  ],
                  "kind": "caught"
                }
              ]
            },
            {
              "batter": "Rashid Khan",
              "bowler": "Noor Ahmad",
              "non_striker": "HE van der Dussen",
              "runs": {
                "batter": 0,
                "extras": 0,
                "total": 0
              }
            },
            {
              "batter": "Rashid Khan",
              "bowler": "Noor Ahmad",
              "non_striker": "HE van der Dussen",
              "runs": {
                "batter": 0,
                "extras": 0,
                "total": 0
              }
            },
            {
              "batter": "Rashid Khan",
              "bowler": "Noor Ahmad",
              "non_striker": "HE van der Dussen",
              "runs": {
                "batter": 0,
                "extras": 0,
                "total": 0
              }
            },
            {
              "batter": "Rashid Khan",
              "bowler": "Noor Ahmad",
              "non_striker": "HE van der Dussen",
              "runs": {
                "batter": 0,
                "extras": 0,
                "total": 0
              }
            }
          ]
        },
        {
          "over": 10,
          "deliveries": [
            {
              "batter": "HE van der Dussen",
              "bowler": "KA Maharaj",
              "non_striker": "Rashid Khan",
              "runs": {
                "batter": 1,
                "extras": 0,
                "total": 1
              }
            },
            {
              "batter": "Rashid Khan",
              "bowler": "KA Maharaj",
              "non_striker": "HE van der Dussen",
              "runs": {
                "batter": 1,
                "extras": 0,
                "total": 1
              }
            },
            {
              "batter": "HE van der Dussen",
              "bowler": "KA Maharaj",
              "non_striker": "Rashid Khan",
              "runs": {
                "batter": 1,
                "extras": 0,
                "total": 1
              }
            },
            {
              "batter": "Rashid Khan",
              "bowler": "KA Maharaj",
              "non_striker": "HE van der Dussen",
              "runs": {
                "batter": 4,
                "extras": 0,
                "total": 4
              }
            },
            {
              "batter": "Rashid Khan",
              "bowler": "KA Maharaj",
              "non_striker": "HE van der Dussen",
              "runs": {
                "batter": 0,
                "extras": 0,
                "total": 0
              }
            },
            {
              "batter": "Rashid Khan",
              "bowler": "KA Maharaj",
              "non_striker": "HE van der Dussen",
              "runs": {
                "batter": 0,
                "extras": 0,
                "total": 0
              }
            }
          ]
        }
      ],
      "powerplays": [
        {
          "from": 0.1,
          "to": 5.6,
          "type": "mandatory"
        }
      ]
    }
  ]
}