{
  "meta": {
    "data_version": "1.1.0",
    "created": "2025-04-30",
    "revision": 1
  },
  "info": {
    "balls_per_over": 6,
    "city": "Lahore",
    "dates": [
      "2025-04-30"
    ],
    "event": {
      "name": "Pakistan Super League",
      "match_number": 19
    },
    "gender": "male",
    "match_type": "T20",
    "officials": {
      "match_referees": [
        "Muhammad Javed"
      ],
      "reserve_umpires": [
        "Tariq Rasheed"
      ],
      "tv_umpires": [
        "Faisal Afridi"
      ],
      "umpires": [
        "Asif Yaqoob",
        "PR Reiffel"
      ]
    },
    "outcome": {
      "winner": "Lahore Qalandars",
      "by": {
        "runs": 88
      }
    },
    "overs": 20,
    "player_of_match": [
      "Sikandar Raza"
    ],
    "players": {
      "Lahore Qalandars": [
        "Fakhar Zaman",
        "Muhammad Naeem",
        "Abdullah Shafique",
        "DJ Mitchell",
        "SW Billings",
        "Sikandar Raza",
        "Asif Ali",
        "Shaheen Shah Afridi",
        "TK Curran",
        "Haris Rauf",
        "Asif Afridi"
      ],
      "Islamabad United": [
        "Sahibzada Farhan",
        "AGS Gous",
        "Agha Salman",
        "Azam Khan",
        "Haider Ali",
        "Shadab Khan",
        "JO Holder",
        "Imad Wasim",
        "BJ Dwarshuis",
        "Naseem Shah",
        "Hunain Shah"
      ]
    },
    "registry": {
      "people": {
        "AGS Gous": "d1305df0",
        "Abdullah Shafique": "fc2fffb5",
        "Agha Salman": "89c16049",
        "Asif Afridi": "9489623e",
        "Asif Ali": "0a4736eb",
        "Asif Yaqoob": "6b35790c",
        "Azam Khan": "ee8f1a6d",
        "BJ Dwarshuis": "e1b9f3a9",
        "DJ Mitchell": "eade4650",
        "Faisal Afridi": "ed0bc503",
        "Fakhar Zaman": "1777c020",
        "Haider Ali": "c13e34f4",
        "Haris Rauf": "24bb1c2f",
        "Hunain Shah": "3b8679bf",
        "Imad Wasim": "9cb8d7a6",
        "JO Holder": "0f721006",
        "Mohammad Nawaz": "3086f7a4",
        "Muhammad Javed": "bde2d0ea",
        "Muhammad Naeem": "e35b7b91",
        "Naseem Shah": "9c9af282",
        "PR Reiffel": "c9354f29",
        "Rishad Hossain": "5935d694",
        "SW Billings": "c16d4035",
        "Sahibzada Farhan": "1aba45cd",
        "Salman Mirza": "7ab1eab7",
        "Shadab Khan": "9de62878",
        "Shaheen Shah Afridi": "45a7e761",
        "Sikandar Raza": "26d041c4",
        "TK Curran": "e86754b2",
        "Tariq Rasheed": "1008518c"
      }
    },
    "season": "2025",
    "team_type": "club",
    "teams": [
      "Lahore Qalandars",
      "Islamabad United"
    ],
    "toss": {
      "decision": "field",
      "winner": "Islamabad United"
    },
    "venue": "Gaddafi Stadium, Lahore"
  },
  "innings": [
    {
      "team": "Lahore Qalandars",
      "overs": [
        {
          "over": 0,
          "deliveries": [
            {
              "batter": "Fakhar Zaman",
              "bowler": "Naseem Shah",
              "non_striker": "Muhammad Naeem",
              "runs": {
                "batter": 4,
                "extras": 0,
                "total": 4
              }
            },
            {
              "batter": "Fakhar Zaman",
              "bowler": "Naseem Shah",
              "non_striker": "Muhammad Naeem",
              "runs": {
                "batter": 0,
                "extras": 0,
                "total": 0
              }
            },
            {
              "batter": "Fakhar Zaman",
              "bowler": "Naseem Shah",
              "non_striker": "Muhammad Naeem",
              "runs": {
                "batter": 0,
                "extras": 0,
                "total": 0
              }
            },
            {
              "batter": "Fakhar Zaman",
              "bowler": "Naseem Shah",
              "non_striker": "Muhammad Naeem",
              "runs": {
                "batter": 0,
                "extras": 0,
                "total": 0
              }
            },
            {
              "batter": "Fakhar Zaman",
              "bowler": "Naseem Shah",
              "non_striker": "Muhammad Naeem",
              "review": {
                "by": "Islamabad United",
                "batter": "Fakhar Zaman",
                "decision": "struck down",
                "umpires_call": true
              },
              "runs": {
                "batter": 0,
                "extras": 0,
                "total": 0
              }
            },
            {
              "batter": "Fakhar Zaman",
              "bowler": "Naseem Shah",
              "non_striker": "Muhammad Naeem",
              "runs": {
                "batter": 0,
                "extras": 0,
                "total": 0
              }
            }
          ]
        },
        {
          "over": 1,
          "deliveries": [
            {
              "batter": "Muhammad Naeem",
              "bowler": "BJ Dwarshuis",
              "non_striker": "Fakhar Zaman",
              "runs": {
                "batter": 0,
                "extras": 0,
                "total": 0
              }
            },
            {
              "batter": "Muhammad Naeem",
              "bowler": "BJ Dwarshuis",
              "non_striker": "Fakhar Zaman",
              "runs": {
                "batter": 0,
                "extras": 0,
                "total": 0
              }
            },
            {
              "batter": "Muhammad Naeem",
              "bowler": "BJ Dwarshuis",
              "non_striker": "Fakhar Zaman",
              "runs": {
                "batter": 4,
                "extras": 0,
                "total": 4
              }
            },
            {
              "batter": "Muhammad Naeem",
              "bowler": "BJ Dwarshuis",
              "non_striker": "Fakhar Zaman",
              "runs": {
                "batter": 0,
                "extras": 0,
                "total": 0
              }
            },
            {
              "batter": "Muhammad Naeem",
              "bowler": "BJ Dwarshuis",
              "extras": {
                "wides": 1
              },
              "non_striker": "Fakhar Zaman",
              "runs": {
                "batter": 0,
                "extras": 1,
                "total": 1
              }
            },
            {
              "batter": "Muhammad Naeem",
              "bowler": "BJ Dwarshuis",
              "non_striker": "Fakhar Zaman",
              "runs": {
                "batter": 0,
                "extras": 0,
                "total": 0
              }
            },
            {
              "batter": "Muhammad Naeem",
              "bowler": "BJ Dwarshuis",
              "non_striker": "Fakhar Zaman",
              "runs": {
                "batter": 1,
                "extras": 0,
                "total": 1
              }
            }
          ]
        },
        {
          "over": 2,
          "deliveries": [
            {
              "batter": "Muhammad Naeem",
              "bowler": "Naseem Shah",
              "non_striker": "Fakhar Zaman",
              "runs": {
                "batter": 0,
                "extras": 0,
                "total": 0
              }
            },
            {
              "batter": "Muhammad Naeem",
              "bowler": "Naseem Shah",
              "non_striker": "Fakhar Zaman",
              "runs": {
                "batter": 0,
                "extras": 0,
                "total": 0
              }
            },
            {
              "batter": "Muhammad Naeem",
              "bowler": "Naseem Shah",
              "non_striker": "Fakhar Zaman",
              "runs": {
                "batter": 0,
                "extras": 0,
                "total": 0
              }
            },
            {
              "batter": "Muhammad Naeem",
              "bowler": "Naseem Shah",
              "non_striker": "Fakhar Zaman",
              "runs": {
                "batter": 2,
                "extras": 0,
                "total": 2
              }
            },
            {
              "batter": "Muhammad Naeem",
              "bowler": "Naseem Shah",
              "non_striker": "Fakhar Zaman",
              "runs": {
                "batter": 0,
                "extras": 0,
                "total": 0
              }
            },
            {
              "batter": "Muhammad Naeem",
              "bowler": "Naseem Shah",
              "extras": {
                "wides": 1
              },
              "non_striker": "Fakhar Zaman",
              "runs": {
                "batter": 0,
                "extras": 1,
                "total": 1
              }
            },
            {
              "batter": "Muhammad Naeem",
              "bowler": "Naseem Shah",
              "non_striker": "Fakhar Zaman",
              "runs": {
                "batter": 0,
                "extras": 0,
                "total": 0
              }
            }
          ]
        },
        {
          "over": 3,
          "deliveries": [
            {
              "batter": "Fakhar Zaman",
              "bowler": "BJ Dwarshuis",
              "non_striker": "Muhammad Naeem",
              "runs": {
                "batter": 0,
                "extras": 0,
                "total": 0
              }
            },
            {
              "batter": "Fakhar Zaman",
              "bowler": "BJ Dwarshuis",
              "non_striker": "Muhammad Naeem",
              "runs": {
                "batter": 0,
                "extras": 0,
                "total": 0
              }
            },
            {
              "batter": "Fakhar Zaman",
              "bowler": "BJ Dwarshuis",
              "non_striker": "Muhammad Naeem",
              "runs": {
                "batter": 1,
                "extras": 0,
                "total": 1
              }
            },
            {
              "batter": "Muhammad Naeem",
              "bowler": "BJ Dwarshuis",
              "non_striker": "Fakhar Zaman",
              "runs": {
                "batter": 4,
                "extras": 0,
                "total": 4
              }
            },
            {
              "batter": "Muhammad Naeem",
              "bowler": "BJ Dwarshuis",
              "non_striker": "Fakhar Zaman",
              "runs": {
                "batter": 4,
                "extras": 0,
                "total": 4
              }
            },
            {
              "batter": "Muhammad Naeem",
              "bowler": "BJ Dwarshuis",
              "non_striker": "Fakhar Zaman",
              "runs": {
                "batter": 4,
                "extras": 0,
                "total": 4
              }
            }
          ]
        },
        {
          "over": 4,
          "deliveries": [
            {
              "batter": "Fakhar Zaman",
              "bowler": "Naseem Shah",
              "non_striker": "Muhammad Naeem",
              "runs": {
                "batter": 6,
                "extras": 0,
                "total": 6
              }
            },
            {
              "batter": "Fakhar Zaman",
              "bowler": "Naseem Shah",
              "non_striker": "Muhammad Naeem",
              "runs": {
                "batter": 1,
                "extras": 0,
                "total": 1
              }
            },
            {
              "batter": "Muhammad Naeem",
              "bowler": "Naseem Shah",
              "non_striker": "Fakhar Zaman",
              "runs": {
                "batter": 0,
                "extras": 0,
                "total": 0
              }
            },
            {
              "batter": "Muhammad Naeem",
              "bowler": "Naseem Shah",
              "non_striker": "Fakhar Zaman",
              "runs": {
                "batter": 0,
                "extras": 0,
                "total": 0
              }
            },
            {
              "batter": "Muhammad Naeem",
              "bowler": "Naseem Shah",
              "non_striker": "Fakhar Zaman",
              "runs": {
                "batter": 6,
                "extras": 0,
                "total": 6
              }
            },
            {
              "batter": "Muhammad Naeem",
              "bowler": "Naseem Shah",
              "non_striker": "Fakhar Zaman",
              "runs": {
                "batter": 0,
                "extras": 0,
                "total": 0
              }
            }
          ]
        },
        {
          "over": 5,
          "deliveries": [
            {
              "batter": "Fakhar Zaman",
              "bowler": "JO Holder",
              "extras": {
                "noballs": 1
              },
              "non_striker": "Muhammad Naeem",
              "runs": {
                "batter": 0,
                "extras": 1,
                "total": 1
              }
            },
            {
              "batter": "Fakhar Zaman",
              "bowler": "JO Holder",
              "extras": {
                "wides": 5
              },
              "non_striker": "Muhammad Naeem",
              "runs": {
                "batter": 0,
                "extras": 5,
                "total": 5
              }
            },
            {
              "batter": "Fakhar Zaman",
              "bowler": "JO Holder",
              "non_striker": "Muhammad Naeem",
              "runs": {
                "batter": 4,
                "extras": 0,
                "total": 4
              }
            },
            {
              "batter": "Fakhar Zaman",
              "bowler": "JO Holder",
              "non_striker": "Muhammad Naeem",
              "runs": {
                "batter": 1,
                "extras": 0,
                "total": 1
              }
            },
            {
              "batter": "Muhammad Naeem",
              "bowler": "JO Holder",
              "non_striker": "Fakhar Zaman",
              "runs": {
                "batter": 0,
                "extras": 0,
                "total": 0
              }
            },
            {
              "batter": "Muhammad Naeem",
              "bowler": "JO Holder",
              "non_striker": "Fakhar Zaman",
              "runs": {
                "batter": 0,
                "extras": 0,
                "total": 0
              }
            },
            {
              "batter": "Muhammad Naeem",
              "bowler": "JO Holder",
              "non_striker": "Fakhar Zaman",
              "runs": {
                "batter": 0,
                "extras": 0,
                "total": 0
              },
              "wickets": [
                {
                  "player_out": "Muhammad Naeem",
                  "fielders": [
                    {
                      "name": "BJ Dwarshuis"
                    }
                  ],
                  "kind": "run out"
                }
              ]
            },
            {
              "batter": "Fakhar Zaman",
              "bowler": "JO Holder",
              "non_striker": "Abdullah Shafique",
              "runs": {
                "batter": 6,
                "extras": 0,
                "total": 6
              }
            }
          ]
        },
        {
          "over": 6,
          "deliveries": [
            {
              "batter": "Abdullah Shafique",
              "bowler": "Shadab Khan",
              "non_striker": "Fakhar Zaman",
              "runs": {
                "batter": 1,
                "extras": 0,
                "total": 1
              }
            },
            {
              "batter": "Fakhar Zaman",
              "bowler": "Shadab Khan",
              "non_striker": "Abdullah Shafique",
              "runs": {
                "batter": 1,
                "extras": 0,
                "total": 1
              }
            },
            {
              "batter": "Abdullah Shafique",
              "bowler": "Shadab Khan",
              "non_striker": "Fakhar Zaman",
              "runs": {
                "batter": 2,
                "extras": 0,
                "total": 2
              }
            },
            {
              "batter": "Abdullah Shafique",
              "bowler": "Shadab Khan",
              "non_striker": "Fakhar Zaman",
              "runs": {
                "batter": 1,
                "extras": 0,
                "total": 1
              }
            },
            {
              "batter": "Fakhar Zaman",
              "bowler": "Shadab Khan",
              "non_striker": "Abdullah Shafique",
              "runs": {
                "batter": 1,
                "extras": 0,
                "total": 1
              }
            },
            {
              "batter": "Abdullah Shafique",
              "bowler": "Shadab Khan",
              "non_striker": "Fakhar Zaman",
              "runs": {
                "batter": 0,
                "extras": 0,
                "total": 0
              }
            }
          ]
        },
        {
          "over": 7,
          "deliveries": [
            {
              "batter": "Fakhar Zaman",
              "bowler": "Hunain Shah",
              "non_striker": "Abdullah Shafique",
              "runs": {
                "batter": 0,
                "extras": 0,
                "total": 0
              }
            },
            {
              "batter": "Fakhar Zaman",
              "bowler": "Hunain Shah",
              "non_striker": "Abdullah Shafique",
              "runs": {
                "batter": 1,
                "extras": 0,
                "total": 1
              }
            },
            {
              "batter": "Abdullah Shafique",
              "bowler": "Hunain Shah",
              "non_striker": "Fakhar Zaman",
              "runs": {
                "batter": 4,
                "extras": 0,
                "total": 4
              }
            },
            {
              "batter": "Abdullah Shafique",
              "bowler": "Hunain Shah",
              "non_striker": "Fakhar Zaman",
              "runs": {
                "batter": 0,
                "extras": 0,
                "total": 0
              }
            },
            {
              "batter": "Abdullah Shafique",
              "bowler": "Hunain Shah",
              "non_striker": "Fakhar Zaman",
              "runs": {
                "batter": 4,
                "extras": 0,
                "total": 4
              }
            },
            {
              "batter": "Abdullah Shafique",
              "bowler": "Hunain Shah",
              "non_striker": "Fakhar Zaman",
              "runs": {
                "batter": 4,
                "extras": 0,
                "total": 4
              }
            }
          ]
        },
        {
          "over": 8,
          "deliveries": [
            {
              "batter": "Fakhar Zaman",
              "bowler": "Shadab Khan",
              "non_striker": "Abdullah Shafique",
              "runs": {
                "batter": 1,
                "extras": 0,
                "total": 1
              }
            },
            {
              "batter": "Abdullah Shafique",
              "bowler": "Shadab Khan",
              "non_striker": "Fakhar Zaman",
              "runs": {
                "batter": 1,
                "extras": 0,
                "total": 1
              }
            },
            {
              "batter": "Fakhar Zaman",
              "bowler": "Shadab Khan",
              "non_striker": "Abdullah Shafique",
              "runs": {
                "batter": 4,
                "extras": 0,
                "total": 4
              }
            },
            {
              "batter": "Fakhar Zaman",
              "bowler": "Shadab Khan",
              "non_striker": "Abdullah Shafique",
              "runs": {
                "batter": 4,
                "extras": 0,
                "total": 4
              }
            },
            {
              "batter": "Fakhar Zaman",
              "bowler": "Shadab Khan",
              "non_striker": "Abdullah Shafique",
              "runs": {
                "batter": 0,
                "extras": 0,
                "total": 0
              }
            },
            {
              "batter": "Fakhar Zaman",
              "bowler": "Shadab Khan",
              "non_striker": "Abdullah Shafique",
              "runs": {
                "batter": 2,
                "extras": 0,
                "total": 2
              }
            }
          ]
        },
        {
          "over": 9,
          "deliveries": [
            {
              "batter": "Abdullah Shafique",
              "bowler": "JO Holder",
              "non_striker": "Fakhar Zaman",
              "runs": {
                "batter": 0,
                "extras": 0,
                "total": 0
              }
            },
            {
              "batter": "Abdullah Shafique",
              "bowler": "JO Holder",
              "non_striker": "Fakhar Zaman",
              "runs": {
                "batter": 1,
                "extras": 0,
                "total": 1
              }
            },
            {
              "batter": "Fakhar Zaman",
              "bowler": "JO Holder",
              "non_striker": "Abdullah Shafique",
              "runs": {
                "batter": 1,
                "extras": 0,
                "total": 1
              }
            },
            {
              "batter": "Abdullah Shafique",
              "bowler": "JO Holder",
              "non_striker": "Fakhar Zaman",
              "runs": {
                "batter": 1,
                "extras": 0,
                "total": 1
              }
            },
            {
              "batter": "Fakhar Zaman",
              "bowler": "JO Holder",
              "non_striker": "Abdullah Shafique",
              "runs": {
                "batter": 0,
                "extras": 0,
                "total": 0
              }
            },
            {
              "batter": "Fakhar Zaman",
              "bowler": "JO Holder",
              "non_striker": "Abdullah Shafique",
              "runs": {
                "batter": 1,
                "extras": 0,
                "total": 1
              }
            }
          ]
        },
        {
          "over": 10,
          "deliveries": [
            {
              "batter": "Fakhar Zaman",
              "bowler": "Imad Wasim",
              "non_striker": "Abdullah Shafique",
              "runs": {
                "batter": 1,
                "extras": 0,
                "total": 1
              }
            },
            {
              "batter": "Abdullah Shafique",
              "bowler": "Imad Wasim",
              "non_striker": "Fakhar Zaman",
              "runs": {
                "batter": 1,
                "extras": 0,
                "total": 1
              }
            },
            {
              "batter": "Fakhar Zaman",
              "bowler": "Imad Wasim",
              "non_striker": "Abdullah Shafique",
              "runs": {
                "batter": 4,
                "extras": 0,
                "total": 4
              }
            },
            {
              "batter": "Fakhar Zaman",
              "bowler": "Imad Wasim",
              "non_striker": "Abdullah Shafique",
              "runs": {
                "batter": 0,
                "extras": 0,
                "total": 0
              },
              "wickets": [
                {
                  "player_out": "Fakhar Zaman",
                  "fielders": [
                    {
                      "name": "Azam Khan"
                    }
                  ],
                  "kind": "stumped"
                }
              ]
            },
            {
              "batter": "DJ Mitchell",
              "bowler": "Imad Wasim",
              "non_striker": "Abdullah Shafique",
              "runs": {
                "batter": 0,
                "extras": 0,
                "total": 0
              }
            },
            {
              "batter": "DJ Mitchell",
              "bowler": "Imad Wasim",
              "non_striker": "Abdullah Shafique",
              "runs": {
                "batter": 1,
                "extras": 0,
                "total": 1
              }
            }
          ]
        },
        {
          "over": 11,
          "deliveries": [
            {
              "batter": "DJ Mitchell",
              "bowler": "Shadab Khan",
              "non_striker": "Abdullah Shafique",
              "runs": {
                "batter": 1,
                "extras": 0,
                "total": 1
              }
            },
            {
              "batter": "Abdullah Shafique",
              "bowler": "Shadab Khan",
              "non_striker": "DJ Mitchell",
              "runs": {
                "batter": 1,
                "extras": 0,
                "total": 1
              }
            },
            {
              "batter": "DJ Mitchell",
              "bowler": "Shadab Khan",
              "non_striker": "Abdullah Shafique",
              "runs": {
                "batter": 1,
                "extras": 0,
                "total": 1
              }
            },
            {
              "batter": "Abdullah Shafique",
              "bowler": "Shadab Khan",
              "non_striker": "DJ Mitchell",
              "runs": {
                "batter": 1,
                "extras": 0,
                "total": 1
              }
            },
            {
              "batter": "DJ Mitchell",
              "bowler": "Shadab Khan",
              "non_striker": "Abdullah Shafique",
              "runs": {
                "batter": 1,
                "extras": 0,
                "total": 1
              }
            },
            {
              "batter": "Abdullah Shafique",
              "bowler": "Shadab Khan",
              "non_striker": "DJ Mitchell",
              "runs": {
                "batter": 0,
                "extras": 0,
                "total": 0
              }
            }
          ]
        },
        {
          "over": 12,
          "deliveries": [
            {
              "batter": "DJ Mitchell",
              "bowler": "Imad Wasim",
              "non_striker": "Abdullah Shafique",
              "runs": {
                "batter": 4,
                "extras": 0,
                "total": 4
              }
            },
            {
              "batter": "DJ Mitchell",
              "bowler": "Imad Wasim",
              "non_striker": "Abdullah Shafique",
              "runs": {
                "batter": 0,
                "extras": 0,
                "total": 0
              }
            },
            {
              "batter": "DJ Mitchell",
              "bowler": "Imad Wasim",
              "extras": {
                "legbyes": 1
              },
              "non_striker": "Abdullah Shafique",
              "runs": {
                "batter": 0,
                "extras": 1,
                "total": 1
              }
            },
            {
              "batter": "Abdullah Shafique",
              "bowler": "Imad Wasim",
              "non_striker": "DJ Mitchell",
              "runs": {
                "batter": 0,
                "extras": 0,
                "total": 0
              },
              "wickets": [
                {
                  "player_out": "Abdullah Shafique",
                  "fielders": [
                    {
                      "name": "Haider Ali"
                    }
                  ],
                  "kind": "caught"
                }
              ]
            },
            {
              "batter": "SW Billings",
              "bowler": "Imad Wasim",
              "non_striker": "DJ Mitchell",
              "runs": {
                "batter": 1,
                "extras": 0,
                "total": 1
              }
            },
            {
              "batter": "DJ Mitchell",
              "bowler": "Imad Wasim",
              "non_striker": "SW Billings",
              "runs": {
                "batter": 0,
                "extras": 0,
                "total": 0
              }
            }
          ]
        },
        {
          "over": 13,
          "deliveries": [
            {
              "batter": "SW Billings",
              "bowler": "Shadab Khan",
              "non_striker": "DJ Mitchell",
              "runs": {
                "batter": 1,
                "extras": 0,
                "total": 1
              }
            },
            {
              "batter": "DJ Mitchell",
              "bowler": "Shadab Khan",
              "non_striker": "SW Billings",
              "runs": {
                "batter": 1,
                "extras": 0,
                "total": 1
              }
            },
            {
              "batter": "SW Billings",
              "bowler": "Shadab Khan",
              "non_striker": "DJ Mitchell",
              "runs": {
                "batter": 1,
                "extras": 0,
                "total": 1
              }
            },
            {
              "batter": "DJ Mitchell",
              "bowler": "Shadab Khan",
              "non_striker": "SW Billings",
              "runs": {
                "batter": 0,
                "extras": 0,
                "total": 0
              }
            },
            {
              "batter": "DJ Mitchell",
              "bowler": "Shadab Khan",
              "non_striker": "SW Billings",
              "runs": {
                "batter": 1,
                "extras": 0,
                "total": 1
              }
            },
            {
              "batter": "SW Billings",
              "bowler": "Shadab Khan",
              "non_striker": "DJ Mitchell",
              "runs": {
                "batter": 0,
                "extras": 0,
                "total": 0
              }
            }
          ]
        },
        {
          "over": 14,
          "deliveries": [
            {
              "batter": "DJ Mitchell",
              "bowler": "Imad Wasim",
              "non_striker": "SW Billings",
              "runs": {
                "batter": 1,
                "extras": 0,
                "total": 1
              }
            },
            {
              "batter": "SW Billings",
              "bowler": "Imad Wasim",
              "non_striker": "DJ Mitchell",
              "runs": {
                "batter": 6,
                "extras": 0,
                "total": 6
              }
            },
            {
              "batter": "SW Billings",
              "bowler": "Imad Wasim",
              "non_striker": "DJ Mitchell",
              "runs": {
                "batter": 4,
                "extras": 0,
                "total": 4
              }
            },
            {
              "batter": "SW Billings",
              "bowler": "Imad Wasim",
              "non_striker": "DJ Mitchell",
              "runs": {
                "batter": 2,
                "extras": 0,
                "total": 2
              }
            },
            {
              "batter": "SW Billings",
              "bowler": "Imad Wasim",
              "non_striker": "DJ Mitchell",
              "runs": {
                "batter": 0,
                "extras": 0,
                "total": 0
              }
            },
            {
              "batter": "SW Billings",
              "bowler": "Imad Wasim",
              "non_striker": "DJ Mitchell",
              "runs": {
                "batter": 1,
                "extras": 0,
                "total": 1
              }
            }
          ]
        },
        {
          "over": 15,
          "deliveries": [
            {
              "batter": "SW Billings",
              "bowler": "JO Holder",
              "extras": {
                "legbyes": 1
              },
              "non_striker": "DJ Mitchell",
              "runs": {
                "batter": 0,
                "extras": 1,
                "total": 1
              }
            },
            {
              "batter": "DJ Mitchell",
              "bowler": "JO Holder",
              "non_striker": "SW Billings",
              "runs": {
                "batter": 4,
                "extras": 0,
                "total": 4
              }
            },
            {
              "batter": "DJ Mitchell",
              "bowler": "JO Holder",
              "non_striker": "SW Billings",
              "runs": {
                "batter": 6,
                "extras": 0,
                "total": 6
              }
            },
            {
              "batter": "DJ Mitchell",
              "bowler": "JO Holder",
              "non_striker": "SW Billings",
              "runs": {
                "batter": 6,
                "extras": 0,
                "total": 6
              }
            },
            {
              "batter": "DJ Mitchell",
              "bowler": "JO Holder",
              "non_striker": "SW Billings",
              "runs": {
                "batter": 1,
                "extras": 0,
                "total": 1
              }
            },
            {
              "batter": "SW Billings",
              "bowler": "JO Holder",
              "non_striker": "DJ Mitchell",
              "runs": {
                "batter": 0,
                "extras": 0,
                "total": 0
              }
            }
          ]
        },
        {
          "over": 16,
          "deliveries": [
            {
              "batter": "DJ Mitchell",
              "bowler": "BJ Dwarshuis",
              "non_striker": "SW Billings",
              "runs": {
                "batter": 0,
                "extras": 0,
                "total": 0
              },
              "wickets": [
                {
                  "player_out": "DJ Mitchell",
                  "fielders": [
                    {
                      "name": "Haider Ali"
                    }
                  ],
                  "kind": "caught"
                }
              ]
            },
            {
              "batter": "Sikandar Raza",
              "bowler": "BJ Dwarshuis",
              "non_striker": "SW Billings",
              "runs": {
                "batter": 2,
                "extras": 0,
                "total": 2
              }
            },
            {
              "batter": "Sikandar Raza",
              "bowler": "BJ Dwarshuis",
              "non_striker": "SW Billings",
              "runs": {
                "batter": 1,
                "extras": 0,
                "total": 1
              }
            },
            {
              "batter": "SW Billings",
              "bowler": "BJ Dwarshuis",
              "non_striker": "Sikandar Raza",
              "runs": {
                "batter": 6,
                "extras": 0,
                "total": 6
              }
            },
            {
              "batter": "SW Billings",
              "bowler": "BJ Dwarshuis",
              "extras": {
                "wides": 1
              },
              "non_striker": "Sikandar Raza",
              "runs": {
                "batter": 0,
                "extras": 1,
                "total": 1
              }
            },
            {
              "batter": "SW Billings",
              "bowler": "BJ Dwarshuis",
              "non_striker": "Sikandar Raza",
              "runs": {
                "batter": 1,
                "extras": 0,
                "total": 1
              }
            },
            {
              "batter": "Sikandar Raza",
              "bowler": "BJ Dwarshuis",
              "non_striker": "SW Billings",
              "runs": {
                "batter": 0,
                "extras": 0,
                "total": 0
              }
            }
          ]
        },
        {
          "over": 17,
          "deliveries": [
            {
              "batter": "SW Billings",
              "bowler": "Naseem Shah",
              "non_striker": "Sikandar Raza",
              "runs": {
                "batter": 6,
                "extras": 0,
                "total": 6
              }
            },
            {
              "batter": "SW Billings",
              "bowler": "Naseem Shah",
              "non_striker": "Sikandar Raza",
              "runs": {
                "batter": 6,
                "extras": 0,
                "total": 6
              }
            },
            {
              "batter": "SW Billings",
              "bowler": "Naseem Shah",
              "non_striker": "Sikandar Raza",
              "runs": {
                "batter": 2,
                "extras": 0,
                "total": 2
              }
            },
            {
              "batter": "SW Billings",
              "bowler": "Naseem Shah",
              "non_striker": "Sikandar Raza",
              "runs": {
                "batter": 1,
                "extras": 0,
                "total": 1
              }
            },
            {
              "batter": "Sikandar Raza",
              "bowler": "Naseem Shah",
              "non_striker": "SW Billings",
              "runs": {
                "batter": 0,
                "extras": 0,
                "total": 0
              }
            },
            {
              "batter": "Sikandar Raza",
              "bowler": "Naseem Shah",
              "non_striker": "SW Billings",
              "runs": {
                "batter": 1,
                "extras": 0,
                "total": 1
              }
            }
          ]
        },
        {
          "over": 18,
          "deliveries": [
            {
              "batter": "Sikandar Raza",
              "bowler": "BJ Dwarshuis",
              "non_striker": "SW Billings",
              "runs": {
                "batter": 4,
                "extras": 0,
                "total": 4
              }
            },
            {
              "batter": "Sikandar Raza",
              "bowler": "BJ Dwarshuis",
              "non_striker": "SW Billings",
              "runs": {
                "batter": 0,
                "extras": 0,
                "total": 0
              }
            },
            {
              "batter": "Sikandar Raza",
              "bowler": "BJ Dwarshuis",
              "non_striker": "SW Billings",
              "runs": {
                "batter": 4,
                "extras": 0,
                "total": 4
              }
            },
            {
              "batter": "Sikandar Raza",
              "bowler": "BJ Dwarshuis",
              "non_striker": "SW Billings",
              "runs": {
                "batter": 6,
                "extras": 0,
                "total": 6
              }
            },
            {
              "batter": "Sikandar Raza",
              "bowler": "BJ Dwarshuis",
              "non_striker": "SW Billings",
              "runs": {
                "batter": 6,
                "extras": 0,
                "total": 6
              }
            },
            {
              "batter": "Sikandar Raza",
              "bowler": "BJ Dwarshuis",
              "non_striker": "SW Billings",
              "runs": {
                "batter": 1,
                "extras": 0,
                "total": 1
              }
            }
          ]
        },
        {
          "over": 19,
          "deliveries": [
            {
              "batter": "Sikandar Raza",
              "bowler": "JO Holder",
              "non_striker": "SW Billings",
              "runs": {
                "batter": 2,
                "extras": 0,
                "total": 2
              }
            },
            {
              "batter": "Sikandar Raza",
              "bowler": "JO Holder",
              "non_striker": "SW Billings",
              "runs": {
                "batter": 6,
                "extras": 0,
                "total": 6
              }
            },
            {
              "batter": "Sikandar Raza",
              "bowler": "JO Holder",
              "extras": {
                "noballs": 1
              },
              "non_striker": "SW Billings",
              "runs": {
                "batter": 0,
                "extras": 1,
                "total": 1
              }
            },
            {
              "batter": "Sikandar Raza",
              "bowler": "JO Holder",
              "non_striker": "SW Billings",
              "runs": {
                "batter": 2,
                "extras": 0,
                "total": 2
              }
            },
            {
              "batter": "Sikandar Raza",
              "bowler": "JO Holder",
              "non_striker": "SW Billings",
              "runs": {
                "batter": 4,
                "extras": 0,
                "total": 4
              }
            },
            {
              "batter": "Sikandar Raza",
              "bowler": "JO Holder",
              "extras": {
                "wides": 1
              },
              "non_striker": "SW Billings",
              "runs": {
                "batter": 0,
                "extras": 1,
                "total": 1
              }
            },
            {
              "batter": "Sikandar Raza",
              "bowler": "JO Holder",
              "non_striker": "SW Billings",
              "runs": {
                "batter": 0,
                "extras": 0,
                "total": 0
              },
              "wickets": [
                {
                  "player_out": "Sikandar Raza",
                  "fielders": [
                    {
                      "name": "Mohammad Nawaz",
                      "substitute": true
                    }
                  ],
                  "kind": "caught"
                }
              ]
            },
            {
              "batter": "Asif Ali",
              "bowler": "JO Holder",
              "non_striker": "SW Billings",
              "runs": {
                "batter": 0,
                "extras": 0,
                "total": 0
              },
              "wickets": [
                {
                  "player_out": "Asif Ali",
                  "fielders": [
                    {
                      "name": "Agha Salman"
                    }
                  ],
                  "kind": "caught"
                }
              ]
            }
          ]
        }
      ],
      "powerplays": [
        {
          "from": 0.1,
          "to": 5.8,
          "type": "mandatory"
        }
      ]
    },
    {
      "team": "Islamabad United",
      "overs": [
        {
          "over": 0,
          "deliveries": [
            {
              "batter": "Sahibzada Farhan",
              "bowler": "Shaheen Shah Afridi",
              "non_striker": "AGS Gous",
              "runs": {
                "batter": 0,
                "extras": 0,
                "total": 0
              }
            },
            {
              "batter": "Sahibzada Farhan",
              "bowler": "Shaheen Shah Afridi",
              "non_striker": "AGS Gous",
              "runs": {
                "batter": 2,
                "extras": 0,
                "total": 2
              }
            },
            {
              "batter": "Sahibzada Farhan",
              "bowler": "Shaheen Shah Afridi",
              "non_striker": "AGS Gous",
              "runs": {
                "batter": 0,
                "extras": 0,
                "total": 0
              }
            },
            {
              "batter": "Sahibzada Farhan",
              "bowler": "Shaheen Shah Afridi",
              "non_striker": "AGS Gous",
              "runs": {
                "batter": 0,
                "extras": 0,
                "total": 0
              }
            },
            {
              "batter": "Sahibzada Farhan",
              "bowler": "Shaheen Shah Afridi",
              "non_striker": "AGS Gous",
              "runs": {
                "batter": 2,
                "extras": 0,
                "total": 2
              }
            },
            {
              "batter": "Sahibzada Farhan",
              "bowler": "Shaheen Shah Afridi",
              "non_striker": "AGS Gous",
              "runs": {
                "batter": 0,
                "extras": 0,
                "total": 0
              }
            }
          ]
        },
        {
          "over": 1,
          "deliveries": [
            {
              "batter": "AGS Gous",
              "bowler": "Asif Afridi",
              "non_striker": "Sahibzada Farhan",
              "runs": {
                "batter": 0,
                "extras": 0,
                "total": 0
              }
            },
            {
              "batter": "AGS Gous",
              "bowler": "Asif Afridi",
              "non_striker": "Sahibzada Farhan",
              "runs": {
                "batter": 1,
                "extras": 0,
                "total": 1
              }
            },
            {
              "batter": "Sahibzada Farhan",
              "bowler": "Asif Afridi",
              "non_striker": "AGS Gous",
              "runs": {
                "batter": 4,
                "extras": 0,
                "total": 4
              }
            },
            {
              "batter": "Sahibzada Farhan",
              "bowler": "Asif Afridi",
              "non_striker": "AGS Gous",
              "runs": {
                "batter": 1,
                "extras": 0,
                "total": 1
              }
            },
            {
              "batter": "AGS Gous",
              "bowler": "Asif Afridi",
              "non_striker": "Sahibzada Farhan",
              "runs": {
                "batter": 0,
                "extras": 0,
                "total": 0
              }
            },
            {
              "batter": "AGS Gous",
              "bowler": "Asif Afridi",
              "non_striker": "Sahibzada Farhan",
              "runs": {
                "batter": 0,
                "extras": 0,
                "total": 0
              }
            }
          ]
        },
        {
          "over": 2,
          "deliveries": [
            {
              "batter": "Sahibzada Farhan",
              "bowler": "Shaheen Shah Afridi",
              "extras": {
                "wides": 1
              },
              "non_striker": "AGS Gous",
              "runs": {
                "batter": 0,
                "extras": 1,
                "total": 1
              }
            },
            {
              "batter": "Sahibzada Farhan",
              "bowler": "Shaheen Shah Afridi",
              "non_striker": "AGS Gous",
              "runs": {
                "batter": 0,
                "extras": 0,
                "total": 0
              }
            },
            {
              "batter": "Sahibzada Farhan",
              "bowler": "Shaheen Shah Afridi",
              "non_striker": "AGS Gous",
              "runs": {
                "batter": 0,
                "extras": 0,
                "total": 0
              },
              "wickets": [
                {
                  "player_out": "Sahibzada Farhan",
                  "fielders": [
                    {
                      "name": "Sikandar Raza"
                    }
                  ],
                  "kind": "caught"
                }
              ]
            },
            {
              "batter": "Agha Salman",
              "bowler": "Shaheen Shah Afridi",
              "non_striker": "AGS Gous",
              "runs": {
                "batter": 0,
                "extras": 0,
                "total": 0
              }
            },
            {
              "batter": "Agha Salman",
              "bowler": "Shaheen Shah Afridi",
              "non_striker": "AGS Gous",
              "runs": {
                "batter": 4,
                "extras": 0,
                "total": 4
              }
            },
            {
              "batter": "Agha Salman",
              "bowler": "Shaheen Shah Afridi",
              "non_striker": "AGS Gous",
              "runs": {
                "batter": 1,
                "extras": 0,
                "total": 1
              }
            },
            {
              "batter": "AGS Gous",
              "bowler": "Shaheen Shah Afridi",
              "non_striker": "Agha Salman",
              "runs": {
                "batter": 0,
                "extras": 0,
                "total": 0
              }
            }
          ]
        },
        {
          "over": 3,
          "deliveries": [
            {
              "batter": "Agha Salman",
              "bowler": "TK Curran",
              "non_striker": "AGS Gous",
              "runs": {
                "batter": 1,
                "extras": 0,
                "total": 1
              }
            },
            {
              "batter": "AGS Gous",
              "bowler": "TK Curran",
              "non_striker": "Agha Salman",
              "runs": {
                "batter": 0,
                "extras": 0,
                "total": 0
              }
            },
            {
              "batter": "AGS Gous",
              "bowler": "TK Curran",
              "non_striker": "Agha Salman",
              "runs": {
                "batter": 6,
                "extras": 0,
                "total": 6
              }
            },
            {
              "batter": "AGS Gous",
              "bowler": "TK Curran",
              "non_striker": "Agha Salman",
              "runs": {
                "batter": 4,
                "extras": 0,
                "total": 4
              }
            },
            {
              "batter": "AGS Gous",
              "bowler": "TK Curran",
              "non_striker": "Agha Salman",
              "runs": {
                "batter": 1,
                "extras": 0,
                "total": 1
              }
            },
            {
              "batter": "Agha Salman",
              "bowler": "TK Curran",
              "non_striker": "AGS Gous",
              "runs": {
                "batter": 0,
                "extras": 0,
                "total": 0
              }
            }
          ]
        },
        {
          "over": 4,
          "deliveries": [
            {
              "batter": "AGS Gous",
              "bowler": "Haris Rauf",
              "non_striker": "Agha Salman",
              "runs": {
                "batter": 1,
                "extras": 0,
                "total": 1
              }
            },
            {
              "batter": "Agha Salman",
              "bowler": "Haris Rauf",
              "non_striker": "AGS Gous",
              "runs": {
                "batter": 0,
                "extras": 0,
                "total": 0
              }
            },
            {
              "batter": "Agha Salman",
              "bowler": "Haris Rauf",
              "non_striker": "AGS Gous",
              "runs": {
                "batter": 6,
                "extras": 0,
                "total": 6
              }
            },
            {
              "batter": "Agha Salman",
              "bowler": "Haris Rauf",
              "non_striker": "AGS Gous",
              "runs": {
                "batter": 1,
                "extras": 0,
                "total": 1
              }
            },
            {
              "batter": "AGS Gous",
              "bowler": "Haris Rauf",
              "non_striker": "Agha Salman",
              "runs": {
                "batter": 1,
                "extras": 0,
                "total": 1
              }
            },
            {
              "batter": "Agha Salman",
              "bowler": "Haris Rauf",
              "non_striker": "AGS Gous",
              "runs": {
                "batter": 1,
                "extras": 0,
                "total": 1
              }
            }
          ]
        },
        {
          "over": 5,
          "deliveries": [
            {
              "batter": "Agha Salman",
              "bowler": "Asif Afridi",
              "non_striker": "AGS Gous",
              "runs": {
                "batter": 6,
                "extras": 0,
                "total": 6
              }
            },
            {
              "batter": "Agha Salman",
              "bowler": "Asif Afridi",
              "non_striker": "AGS Gous",
              "runs": {
                "batter": 0,
                "extras": 0,
                "total": 0
              }
            },
            {
              "batter": "Agha Salman",
              "bowler": "Asif Afridi",
              "non_striker": "AGS Gous",
              "runs": {
                "batter": 0,
                "extras": 0,
                "total": 0
              }
            },
            {
              "batter": "Agha Salman",
              "bowler": "Asif Afridi",
              "non_striker": "AGS Gous",
              "runs": {
                "batter": 0,
                "extras": 0,
                "total": 0
              }
            },
            {
              "batter": "Agha Salman",
              "bowler": "Asif Afridi",
              "non_striker": "AGS Gous",
              "runs": {
                "batter": 1,
                "extras": 0,
                "total": 1
              }
            },
            {
              "batter": "AGS Gous",
              "bowler": "Asif Afridi",
              "non_striker": "Agha Salman",
              "runs": {
                "batter": 4,
                "extras": 0,
                "total": 4
              }
            }
          ]
        },
        {
          "over": 6,
          "deliveries": [
            {
              "batter": "Agha Salman",
              "bowler": "TK Curran",
              "non_striker": "AGS Gous",
              "runs": {
                "batter": 4,
                "extras": 0,
                "total": 4
              }
            },
            {
              "batter": "Agha Salman",
              "bowler": "TK Curran",
              "non_striker": "AGS Gous",
              "runs": {
                "batter": 0,
                "extras": 0,
                "total": 0
              }
            },
            {
              "batter": "Agha Salman",
              "bowler": "TK Curran",
              "non_striker": "AGS Gous",
              "runs": {
                "batter": 1,
                "extras": 0,
                "total": 1
              }
            },
            {
              "batter": "AGS Gous",
              "bowler": "TK Curran",
              "non_striker": "Agha Salman",
              "runs": {
                "batter": 2,
                "extras": 0,
                "total": 2
              }
            },
            {
              "batter": "AGS Gous",
              "bowler": "TK Curran",
              "non_striker": "Agha Salman",
              "runs": {
                "batter": 1,
                "extras": 0,
                "total": 1
              }
            },
            {
              "batter": "Agha Salman",
              "bowler": "TK Curran",
              "non_striker": "AGS Gous",
              "runs": {
                "batter": 1,
                "extras": 0,
                "total": 1
              }
            }
          ]
        },
        {
          "over": 7,
          "deliveries": [
            {
              "batter": "Agha Salman",
              "bowler": "Asif Afridi",
              "non_striker": "AGS Gous",
              "runs": {
                "batter": 1,
                "extras": 0,
                "total": 1
              }
            },
            {
              "batter": "AGS Gous",
              "bowler": "Asif Afridi",
              "non_striker": "Agha Salman",
              "runs": {
                "batter": 0,
                "extras": 0,
                "total": 0
              }
            },
            {
              "batter": "AGS Gous",
              "bowler": "Asif Afridi",
              "non_striker": "Agha Salman",
              "runs": {
                "batter": 0,
                "extras": 0,
                "total": 0
              }
            },
            {
              "batter": "AGS Gous",
              "bowler": "Asif Afridi",
              "non_striker": "Agha Salman",
              "runs": {
                "batter": 2,
                "extras": 0,
                "total": 2
              }
            },
            {
              "batter": "AGS Gous",
              "bowler": "Asif Afridi",
              "non_striker": "Agha Salman",
              "runs": {
                "batter": 1,
                "extras": 0,
                "total": 1
              }
            },
            {
              "batter": "Agha Salman",
              "bowler": "Asif Afridi",
              "non_striker": "AGS Gous",
              "runs": {
                "batter": 0,
                "extras": 0,
                "total": 0
              }
            }
          ]
        },
        {
          "over": 8,
          "deliveries": [
            {
              "batter": "AGS Gous",
              "bowler": "DJ Mitchell",
              "non_striker": "Agha Salman",
              "runs": {
                "batter": 6,
                "extras": 0,
                "total": 6
              }
            },
            {
              "batter": "AGS Gous",
              "bowler": "DJ Mitchell",
              "non_striker": "Agha Salman",
              "runs": {
                "batter": 2,
                "extras": 0,
                "total": 2
              }
            },
            {
              "batter": "AGS Gous",
              "bowler": "DJ Mitchell",
              "non_striker": "Agha Salman",
              "runs": {
                "batter": 1,
                "extras": 0,
                "total": 1
              }
            },
            {
              "batter": "Agha Salman",
              "bowler": "DJ Mitchell",
              "non_striker": "AGS Gous",
              "runs": {
                "batter": 1,
                "extras": 0,
                "total": 1
              }
            },
            {
              "batter": "AGS Gous",
              "bowler": "DJ Mitchell",
              "non_striker": "Agha Salman",
              "runs": {
                "batter": 1,
                "extras": 0,
                "total": 1
              }
            },
            {
              "batter": "Agha Salman",
              "bowler": "DJ Mitchell",
              "non_striker": "AGS Gous",
              "runs": {
                "batter": 1,
                "extras": 0,
                "total": 1
              }
            }
          ]
        },
        {
          "over": 9,
          "deliveries": [
            {
              "batter": "Agha Salman",
              "bowler": "Sikandar Raza",
              "non_striker": "AGS Gous",
              "runs": {
                "batter": 0,
                "extras": 0,
                "total": 0
              }
            },
            {
              "batter": "Agha Salman",
              "bowler": "Sikandar Raza",
              "non_striker": "AGS Gous",
              "runs": {
                "batter": 6,
                "extras": 0,
                "total": 6
              }
            },
            {
              "batter": "Agha Salman",
              "bowler": "Sikandar Raza",
              "non_striker": "AGS Gous",
              "runs": {
                "batter": 0,
                "extras": 0,
                "total": 0
              },
              "wickets": [
                {
                  "player_out": "Agha Salman",
                  "kind": "bowled"
                }
              ]
            },
            {
              "batter": "Azam Khan",
              "bowler": "Sikandar Raza",
              "non_striker": "AGS Gous",
              "runs": {
                "batter": 1,
                "extras": 0,
                "total": 1
              }
            },
            {
              "batter": "AGS Gous",
              "bowler": "Sikandar Raza",
              "non_striker": "Azam Khan",
              "runs": {
                "batter": 6,
                "extras": 0,
                "total": 6
              }
            },
            {
              "batter": "AGS Gous",
              "bowler": "Sikandar Raza",
              "non_striker": "Azam Khan",
              "runs": {
                "batter": 0,
                "extras": 0,
                "total": 0
              }
            }
          ]
        },
        {
          "over": 10,
          "deliveries": [
            {
              "batter": "Azam Khan",
              "bowler": "Haris Rauf",
              "non_striker": "AGS Gous",
              "review": {
                "by": "Islamabad United",
                "batter": "Azam Khan",
                "decision": "struck down"
              },
              "runs": {
                "batter": 0,
                "extras": 0,
                "total": 0
              },
              "wickets": [
                {
                  "player_out": "Azam Khan",
                  "kind": "lbw"
                }
              ]
            },
            {
              "batter": "Haider Ali",
              "bowler": "Haris Rauf",
              "non_striker": "AGS Gous",
              "runs": {
                "batter": 0,
                "extras": 0,
                "total": 0
              }
            },
            {
              "batter": "Haider Ali",
              "bowler": "Haris Rauf",
              "non_striker": "AGS Gous",
              "runs": {
                "batter": 4,
                "extras": 0,
                "total": 4
              }
            },
            {
              "batter": "Haider Ali",
              "bowler": "Haris Rauf",
              "non_striker": "AGS Gous",
              "runs": {
                "batter": 0,
                "extras": 0,
                "total": 0
              }
            },
            {
              "batter": "Haider Ali",
              "bowler": "Haris Rauf",
              "non_striker": "AGS Gous",
              "runs": {
                "batter": 1,
                "extras": 0,
                "total": 1
              }
            },
            {
              "batter": "AGS Gous",
              "bowler": "Haris Rauf",
              "non_striker": "Haider Ali",
              "runs": {
                "batter": 0,
                "extras": 0,
                "total": 0
              }
            }
          ]
        },
        {
          "over": 11,
          "deliveries": [
            {
              "batter": "Haider Ali",
              "bowler": "Asif Afridi",
              "non_striker": "AGS Gous",
              "runs": {
                "batter": 0,
                "extras": 0,
                "total": 0
              }
            },
            {
              "batter": "Haider Ali",
              "bowler": "Asif Afridi",
              "non_striker": "AGS Gous",
              "runs": {
                "batter": 0,
                "extras": 0,
                "total": 0
              },
              "wickets": [
                {
                  "player_out": "Haider Ali",
                  "fielders": [
                    {
                      "name": "TK Curran"
                    }
                  ],
                  "kind": "caught"
                }
              ]
            },
            {
              "batter": "Shadab Khan",
              "bowler": "Asif Afridi",
              "non_striker": "AGS Gous",
              "runs": {
                "batter": 1,
                "extras": 0,
                "total": 1
              }
            },
            {
              "batter": "AGS Gous",
              "bowler": "Asif Afridi",
              "non_striker": "Shadab Khan",
              "runs": {
                "batter": 1,
                "extras": 0,
                "total": 1
              }
            },
            {
              "batter": "Shadab Khan",
              "bowler": "Asif Afridi",
              "non_striker": "AGS Gous",
              "runs": {
                "batter": 0,
                "extras": 0,
                "total": 0
              }
            },
            {
              "batter": "Shadab Khan",
              "bowler": "Asif Afridi",
              "non_striker": "AGS Gous",
              "runs": {
                "batter": 1,
                "extras": 0,
                "total": 1
              }
            }
          ]
        },
        {
          "over": 12,
          "deliveries": [
            {
              "batter": "Shadab Khan",
              "bowler": "Haris Rauf",
              "non_striker": "AGS Gous",
              "runs": {
                "batter": 4,
                "extras": 0,
                "total": 4
              }
            },
            {
              "batter": "Shadab Khan",
              "bowler": "Haris Rauf",
              "non_striker": "AGS Gous",
              "runs": {
                "batter": 4,
                "extras": 0,
                "total": 4
              }
            },
            {
              "batter": "Shadab Khan",
              "bowler": "Haris Rauf",
              "non_striker": "AGS Gous",
              "runs": {
                "batter": 1,
                "extras": 0,
                "total": 1
              }
            },
            {
              "batter": "AGS Gous",
              "bowler": "Haris Rauf",
              "non_striker": "Shadab Khan",
              "runs": {
                "batter": 0,
                "extras": 0,
                "total": 0
              },
              "wickets": [
                {
                  "player_out": "AGS Gous",
                  "kind": "bowled"
                }
              ]
            },
            {
              "batter": "JO Holder",
              "bowler": "Haris Rauf",
              "non_striker": "Shadab Khan",
              "runs": {
                "batter": 0,
                "extras": 0,
                "total": 0
              },
              "wickets": [
                {
                  "player_out": "JO Holder",
                  "fielders": [
                    {
                      "name": "SW Billings"
                    }
                  ],
                  "kind": "caught"
                }
              ]
            },
            {
              "batter": "Imad Wasim",
              "bowler": "Haris Rauf",
              "non_striker": "Shadab Khan",
              "runs": {
                "batter": 0,
                "extras": 0,
                "total": 0
              }
            }
          ]
        },
        {
          "over": 13,
          "deliveries": [
            {
              "batter": "Shadab Khan",
              "bowler": "Sikandar Raza",
              "non_striker": "Imad Wasim",
              "runs": {
                "batter": 1,
                "extras": 0,
                "total": 1
              }
            },
            {
              "batter": "Imad Wasim",
              "bowler": "Sikandar Raza",
              "non_striker": "Shadab Khan",
              "review": {
                "by": "Lahore Qalandars",
                "batter": "Imad Wasim",
                "decision": "struck down",
                "umpires_call": true
              },
              "runs": {
                "batter": 0,
                "extras": 0,
                "total": 0
              }
            },
            {
              "batter": "Imad Wasim",
              "bowler": "Sikandar Raza",
              "non_striker": "Shadab Khan",
              "runs": {
                "batter": 0,
                "extras": 0,
                "total": 0
              }
            },
            {
              "batter": "Imad Wasim",
              "bowler": "Sikandar Raza",
              "non_striker": "Shadab Khan",
              "runs": {
                "batter": 0,
                "extras": 0,
                "total": 0
              }
            },
            {
              "batter": "Imad Wasim",
              "bowler": "Sikandar Raza",
              "non_striker": "Shadab Khan",
              "runs": {
                "batter": 0,
                "extras": 0,
                "total": 0
              }
            },
            {
              "batter": "Imad Wasim",
              "bowler": "Sikandar Raza",
              "non_striker": "Shadab Khan",
              "runs": {
                "batter": 1,
                "extras": 0,
                "total": 1
              }
            }
          ]
        },
        {
          "over": 14,
          "deliveries": [
            {
              "batter": "Imad Wasim",
              "bowler": "TK Curran",
              "non_striker": "Shadab Khan",
              "runs": {
                "batter": 0,
                "extras": 0,
                "total": 0
              }
            },
            {
              "batter": "Imad Wasim",
              "bowler": "TK Curran",
              "non_striker": "Shadab Khan",
              "runs": {
                "batter": 1,
                "extras": 0,
                "total": 1
              }
            },
            {
              "batter": "Shadab Khan",
              "bowler": "TK Curran",
              "non_striker": "Imad Wasim",
              "runs": {
                "batter": 1,
                "extras": 0,
                "total": 1
              }
            },
            {
              "batter": "Imad Wasim",
              "bowler": "TK Curran",
              "non_striker": "Shadab Khan",
              "runs": {
                "batter": 0,
                "extras": 0,
                "total": 0
              }
            },
            {
              "batter": "Imad Wasim",
              "bowler": "TK Curran",
              "non_striker": "Shadab Khan",
              "runs": {
                "batter": 0,
                "extras": 0,
                "total": 0
              },
              "wickets": [
                {
                  "player_out": "Imad Wasim",
                  "fielders": [
                    {
                      "name": "Shaheen Shah Afridi"
                    }
                  ],
                  "kind": "caught"
                }
              ]
            },
            {
              "batter": "BJ Dwarshuis",
              "bowler": "TK Curran",
              "non_striker": "Shadab Khan",
              "runs": {
                "batter": 1,
                "extras": 0,
                "total": 1
              }
            }
          ]
        },
        {
          "over": 15,
          "deliveries": [
            {
              "batter": "BJ Dwarshuis",
              "bowler": "Sikandar Raza",
              "non_striker": "Shadab Khan",
              "runs": {
                "batter": 0,
                "extras": 0,
                "total": 0
              },
              "wickets": [
                {
                  "player_out": "BJ Dwarshuis",
                  "fielders": [
                    {
                      "name": "Salman Mirza",
                      "substitute": true
                    }
                  ],
                  "kind": "caught"
                }
              ]
            },
            {
              "batter": "Naseem Shah",
              "bowler": "Sikandar Raza",
              "non_striker": "Shadab Khan",
              "runs": {
                "batter": 4,
                "extras": 0,
                "total": 4
              }
            },
            {
              "batter": "Naseem Shah",
              "bowler": "Sikandar Raza",
              "non_striker": "Shadab Khan",
              "runs": {
                "batter": 1,
                "extras": 0,
                "total": 1
              }
            },
            {
              "batter": "Shadab Khan",
              "bowler": "Sikandar Raza",
              "non_striker": "Naseem Shah",
              "runs": {
                "batter": 0,
                "extras": 0,
                "total": 0
              }
            },
            {
              "batter": "Shadab Khan",
              "bowler": "Sikandar Raza",
              "non_striker": "Naseem Shah",
              "runs": {
                "batter": 0,
                "extras": 0,
                "total": 0
              },
              "wickets": [
                {
                  "player_out": "Shadab Khan",
                  "fielders": [
                    {
                      "name": "Rishad Hossain",
                      "substitute": true
                    }
                  ],
                  "kind": "caught"
                }
              ]
            },
            {
              "batter": "Hunain Shah",
              "bowler": "Sikandar Raza",
              "non_striker": "Naseem Shah",
              "runs": {
                "batter": 0,
                "extras": 0,
                "total": 0
              }
            }
          ]
        },
        {
          "over": 16,
          "deliveries": [
            {
              "batter": "Naseem Shah",
              "bowler": "Haris Rauf",
              "non_striker": "Hunain Shah",
              "runs": {
                "batter": 2,
                "extras": 0,
                "total": 2
              }
            },
            {
              "batter": "Naseem Shah",
              "bowler": "Haris Rauf",
              "non_striker": "Hunain Shah",
              "runs": {
                "batter": 0,
                "extras": 0,
                "total": 0
              }
            },
            {
              "batter": "Naseem Shah",
              "bowler": "Haris Rauf",
              "extras": {
                "wides": 1
              },
              "non_striker": "Hunain Shah",
              "runs": {
                "batter": 0,
                "extras": 1,
                "total": 1
              }
            },
            {
              "batter": "Naseem Shah",
              "bowler": "Haris Rauf",
              "non_striker": "Hunain Shah",
              "runs": {
                "batter": 0,
                "extras": 0,
                "total": 0
              }
            },
            {
              "batter": "Naseem Shah",
              "bowler": "Haris Rauf",
              "non_striker": "Hunain Shah",
              "runs": {
                "batter": 4,
                "extras": 0,
                "total": 4
              }
            },
            {
              "batter": "Naseem Shah",
              "bowler": "Haris Rauf",
              "non_striker": "Hunain Shah",
              "runs": {
                "batter": 0,
                "extras": 0,
                "total": 0
              },
              "wickets": [
                {
                  "player_out": "Naseem Shah",
                  "fielders": [
                    {
                      "name": "Muhammad Naeem"
                    }
                  ],
                  "kind": "caught"
                }
              ]
            }
          ]
        }
      ],
      "powerplays": [
        {
          "from": 0.1,
          "to": 5.6,
          "type": "mandatory"
        }
      ],
      "target": {
        "overs": 20,
        "runs": 210
      }
    }
  ]
}